{
	"autorun": true,
	"cacheVersn": 0,
	"closureScript": "",
	"color": "#9FA8DA",
	"days": 0,
	"daysR": 0,
	"default": false,
	"definitionId": "",
	"detached": false,
	"disabled": false,
	"extractSettings": {
		"fieldCliNameToExtractSettings": {},
		"mode": "All"
	},
	"fromServerVersion": "",
	"hours": 0,
	"hoursR": 0,
	"id": "PANW IoT 3rd Party AIMS Work Order",
	"itemVersion": "",
	"layout": "",
	"locked": false,
	"name": "PANW IoT 3rd Party AIMS Work Order",
	"onChangeRepAlg": 1,
	"packID": "",
	"packName": "",
	"playbookId": "91a6bd11-8c73-4b25-83b4-e8fad47f03fb",
	"preProcessingScript": "",
	"propagationLabels": [
		"all"
	],
	"readonly": false,
	"reputationCalc": 0,
	"system": false,
	"toServerVersion": "",
	"version": -1,
	"weeks": 0,
	"weeksR": 0
}